{
  "0": "阿比西尼亚猫",
  "1": "孟加拉猫",
  "2": "伯曼猫",
  "3": "孟买猫",
  "4": "英国短毛猫",
  "5": "埃及猫",
  "6": "缅因猫",
  "7": "波斯猫",
  "8": "布偶猫",
  "9": "俄罗斯蓝猫",
  "10": "暹罗猫",
  "11": "加拿大无毛猫",
  "12": "美国斗牛犬",
  "13": "美国斗牛梗",
  "14": "巴吉度猎犬",
  "15": "比格",
  "16": "拳师犬",
  "17": "吉娃娃",
  "18": "英国可卡犬",
  "19": "英国雪达犬",
  "20": "德国短毛指示犬",
  "21": "大白熊犬",
  "22": "哈瓦那犬",
  "23": "日本狆",
  "24": "荷兰毛狮犬",
  "25": "莱昂贝格犬",
  "26": "都柏文犬",
  "27": "纽芬兰犬",
  "28": "博美犬",
  "29": "哈巴狗",
  "30": "圣伯纳犬",
  "31": "萨摩耶犬",
  "32": "苏格兰梗",
  "33": "柴犬",
  "34": "斯塔福郡斗牛梗",
  "35": "爱尔兰软毛梗",
  "36": "约克夏梗犬"
}