{
  "0": "Antelope",
  "1": "Badger",
  "2": "Bat",
  "3": "Bear",
  "4": "Bee",
  "5": "Beetle",
  "6": "Bison",
  "7": "Boar",
  "8": "Butterfly",
  "9": "Cat",
  "10": "Caterpillar",
  "11": "Chimpanzee",
  "12": "Cockroach",
  "13": "Cow",
  "14": "Coyote",
  "15": "Crab",
  "16": "Crow",
  "17": "Deer",
  "18": "Dog",
  "19": "Dolphin",
  "20": "Donkey",
  "21": "Dragonfly",
  "22": "Duck",
  "23": "Eagle",
  "24": "Elephant",
  "25": "Flamingo",
  "26": "Fly",
  "27": "Fox",
  "28": "Goat",
  "29": "Goldfish",
  "30": "Goose",
  "31": "Gorilla",
  "32": "Grasshopper",
  "33": "Hamster",
  "34": "Hare",
  "35": "Hedgehog",
  "36": "Hippopotamus",
  "37": "Hornbill",
  "38": "Horse",
  "39": "Hummingbird",
  "40": "Hyena",
  "41": "Jellyfish",
  "42": "Kangaroo",
  "43": "Koala",
  "44": "Ladybug",
  "45": "Leopard",
  "46": "Lion",
  "47": "Lizard",
  "48": "Lobster",
  "49": "Mosquito",
  "50": "Moth",
  "51": "Mouse",
  "52": "Octopus",
  "53": "Okapi",
  "54": "Orangutan",
  "55": "Otter",
  "56": "Owl",
  "57": "Ox",
  "58": "Oyster",
  "59": "Panda",
  "60": "Parrot",
  "61": "Pelican",
  "62": "Penguin",
  "63": "Pig",
  "64": "Pigeon",
  "65": "Porcupine",
  "66": "Possum",
  "67": "Raccoon",
  "68": "Rat",
  "69": "Reindeer",
  "70": "Rhinoceros",
  "71": "Sandpiper",
  "72": "Seahorse",
  "73": "Seal",
  "74": "Shark",
  "75": "Sheep",
  "76": "Snake",
  "77": "Sparrow",
  "78": "Squid",
  "79": "Squirrel",
  "80": "Starfish",
  "81": "Swan",
  "82": "Tiger",
  "83": "Turkey",
  "84": "Turtle",
  "85": "Whale",
  "86": "Wolf",
  "87": "Wombat",
  "88": "Woodpecker",
  "89": "Zebra"
}